clarifai_datautils/__init__.py
clarifai_datautils/errors.py
clarifai_datautils/base/__init__.py
clarifai_datautils/base/features.py
clarifai_datautils/constants/__init__.py
clarifai_datautils/constants/annotations.py
clarifai_datautils/constants/base.py
clarifai_datautils/constants/pipeline.py
clarifai_datautils/image/__init__.py
clarifai_datautils/image/annotation_conversion/README.md
clarifai_datautils/image/annotation_conversion/__init__.py
clarifai_datautils/image/annotation_conversion/annotations.py
clarifai_datautils/image/annotation_conversion/loaders.py
clarifai_datautils/image/annotation_conversion/utils.py
clarifai_datautils/multimodal/__init__.py
clarifai_datautils/multimodal/pipeline/Docx.py
clarifai_datautils/multimodal/pipeline/Markdown.py
clarifai_datautils/multimodal/pipeline/PDF.py
clarifai_datautils/multimodal/pipeline/README.md
clarifai_datautils/multimodal/pipeline/Text.py
clarifai_datautils/multimodal/pipeline/base.py
clarifai_datautils/multimodal/pipeline/basetransform.py
clarifai_datautils/multimodal/pipeline/cleaners.py
clarifai_datautils/multimodal/pipeline/custom_pipeline.py
clarifai_datautils/multimodal/pipeline/extractors.py
clarifai_datautils/multimodal/pipeline/loaders.py
clarifai_datautils/multimodal/pipeline/summarizer.py
clarifai_datautils-0.0.7.dist-info/LICENSE
clarifai_datautils-0.0.7.dist-info/METADATA
clarifai_datautils-0.0.7.dist-info/WHEEL
clarifai_datautils-0.0.7.dist-info/top_level.txt
clarifai_datautils-0.0.7.dist-info/RECORD
