Metadata-Version: 2.2
Name: clarifai-datautils
Version: 0.0.7
Summary: Clarifai Data Utils
Home-page: https://github.com/Clarifai/clarifai-python-datautils
Author: Clarifai
Author-email: support@clarifai.com
License: Apache 2.0
Classifier: Topic :: Scientific/Engineering :: Artificial Intelligence
Classifier: Programming Language :: Python :: 3
Classifier: Programming Language :: Python :: 3 :: Only
Classifier: Programming Language :: Python :: 3.9
Classifier: Programming Language :: Python :: 3.10
Classifier: Programming Language :: Python :: 3.11
Classifier: Programming Language :: Python :: 3.12
Classifier: Programming Language :: Python :: Implementation :: CPython
Classifier: License :: OSI Approved :: Apache Software License
Classifier: Operating System :: OS Independent
Requires-Python: >=3.8
License-File: LICENSE
Requires-Dist: llama-index-core==0.10.33
Requires-Dist: llama-index-llms-clarifai==0.1.2
Requires-Dist: pi_heif==0.18.0
Requires-Dist: markdown==3.7
Requires-Dist: python-docx==1.1.2
Requires-Dist: schema==0.7.5
Provides-Extra: annotations
Requires-Dist: datumaro==1.6.1; extra == "annotations"
Dynamic: author
Dynamic: author-email
Dynamic: classifier
Dynamic: description
Dynamic: description-content-type
Dynamic: home-page
Dynamic: license
Dynamic: provides-extra
Dynamic: requires-dist
Dynamic: requires-python
Dynamic: summary
